MANIFEST.in
README.md
setup.py
brilview/__init__.py
brilview/_version.py
brilview/brilview_flask_app.py
brilview/bvconfig.py
brilview/bvlogging.py
brilview/common.py
brilview/queryrouter.py
brilview.egg-info/PKG-INFO
brilview.egg-info/SOURCES.txt
brilview.egg-info/dependency_links.txt
brilview.egg-info/entry_points.txt
brilview.egg-info/top_level.txt
brilview/cli/__init__.py
brilview/cli/brilview_main.py
brilview/cli/test.py
brilview/data/brilview_dev.yaml
brilview/data/brilview_prod.yaml
brilview/data/brilview_user.yaml
brilview/handlers/__init__.py
brilview/handlers/cmmdhandler.py
brilview/handlers/lumidbhandler.py
brilview/handlers/utils.py
brilview/web/dist/0.b350f9dd0a59541518c0.chunk.js
brilview/web/dist/1.03bbdf91fae46468f0e4.chunk.js
brilview/web/dist/2.c0b97f87b8e0bf758faf.chunk.js
brilview/web/dist/3rdpartylicenses.txt
brilview/web/dist/favicon.ico
brilview/web/dist/index.html
brilview/web/dist/inline.d7476347930a815ae7a7.bundle.js
brilview/web/dist/main.b229491db4eceaa56c76.bundle.js
brilview/web/dist/polyfills.3fd38881bdc855213548.bundle.js
brilview/web/dist/scripts.0d3bcfb27ff78f49c618.bundle.js
brilview/web/dist/styles.0f1e8b08a0b3228f60e3.bundle.css
brilview/web/dist/assets/atlaslumi_thumbnail.png
brilview/web/dist/assets/bxlumi_thumbnail.png
brilview/web/dist/assets/livebest_thumbnail.png
brilview/web/dist/assets/totlumi_thumbnail.png