Metadata-Version: 1.1
Name: brilview
Version: 1.3.3
Summary: bril data viewer
Home-page: https://github.com/jonasdaugalas/brilview
Author: Jonas Daugalas,Zhen Xie
Author-email: UNKNOWN
License: MIT
Download-URL: https://github.com/jonasdaugalas/brilws/tarball/1.3.3
Platform: UNKNOWN
